string_conditions/__init__.py
string_conditions/__main__.py
string_conditions/errors.py
string_conditions/visitor.py
string_conditions/tests/__init__.py
string_conditions/tests/test_condition.py
string_conditions-0.0.1.dist-info/LICENSE
string_conditions-0.0.1.dist-info/METADATA
string_conditions-0.0.1.dist-info/WHEEL
string_conditions-0.0.1.dist-info/entry_points.txt
string_conditions-0.0.1.dist-info/top_level.txt
string_conditions-0.0.1.dist-info/RECORD
