Metadata-Version: 2.1
Name: string-conditions
Version: 0.0.1
Summary: Evaluate string Python conditions while keeping control on functions and variables accessible
Author: Martin DENIZET
License: MIT
Project-URL: Homepage, https://github.com/martin-denizet/string_conditions
Project-URL: Changelog, https://github.com/martin-denizet/string_conditions/releases
Project-URL: Issues, https://github.com/martin-denizet/string_conditions/issues
Classifier: License :: OSI Approved :: MIT License
Classifier: Development Status :: 4 - Beta
Classifier: Operating System :: OS Independent
Classifier: Topic :: Software Development
Classifier: Natural Language :: English
Classifier: Programming Language :: Python :: 3
Classifier: Programming Language :: Python :: 3 :: Only
Classifier: Programming Language :: Python :: 3.8
Classifier: Programming Language :: Python :: 3.9
Classifier: Programming Language :: Python :: 3.10
Classifier: Programming Language :: Python :: 3.11
License-File: LICENSE
